mola/__init__.py
mola/math_tools.py
mola/misc.py
mola/naming_conventions.py
mola/bin/mola_available
mola/bin/mola_clean
mola/bin/mola_merge_containers
mola/bin/mola_mesh_to_ngon
mola/bin/mola_plot
mola/bin/mola_prepare
mola/bin/mola_repatriate
mola/bin/mola_seelog
mola/bin/mola_update
mola/bin/mola_version
mola/bin/mola_watchdir
mola/bin/mola_watchqueue
mola/cfd/__init__.py
mola/cfd/bodyforce/__init__.py
mola/cfd/compute/__init__.py
mola/cfd/compute/compute.py
mola/cfd/compute/solver_elsa.py
mola/cfd/compute/solver_fast.py
mola/cfd/compute/solver_sonics.py
mola/cfd/compute/read_cfd_files/__init__.py
mola/cfd/compute/read_cfd_files/read_cfd_files.py
mola/cfd/compute/read_cfd_files/solver_elsa.py
mola/cfd/compute/read_cfd_files/solver_fast.py
mola/cfd/compute/read_cfd_files/solver_sonics.py
mola/cfd/coprocess/__init__.py
mola/cfd/coprocess/manager.py
mola/cfd/coprocess/probes.py
mola/cfd/coprocess/solver_elsa.py
mola/cfd/coprocess/solver_fast.py
mola/cfd/coprocess/solver_sonics.py
mola/cfd/coprocess/stopping_criteria.py
mola/cfd/coprocess/tools.py
mola/cfd/coprocess/user_interface.py
mola/cfd/postprocess/__init__.py
mola/cfd/postprocess/compute.py
mola/cfd/postprocess/extractions.py
mola/cfd/postprocess/extractions_with_cassiopee/__init__.py
mola/cfd/postprocess/extractions_with_cassiopee/extract_bc.py
mola/cfd/postprocess/extractions_with_cassiopee/iso_surface.py
mola/cfd/postprocess/extractions_with_cassiopee/tools.py
mola/cfd/postprocess/extractions_with_maia/__init__.py
mola/cfd/postprocess/extractions_with_maia/extract_bc.py
mola/cfd/postprocess/extractions_with_maia/iso_surface.py
mola/cfd/postprocess/interpolation/__init__.py
mola/cfd/postprocess/interpolation/interpolation.py
mola/cfd/postprocess/remove_cfd_files/__init__.py
mola/cfd/postprocess/remove_cfd_files/remove_cfd_files.py
mola/cfd/postprocess/remove_cfd_files/solver_elsa.py
mola/cfd/postprocess/remove_cfd_files/solver_fast.py
mola/cfd/postprocess/remove_cfd_files/solver_sonics.py
mola_workflow-2.0.0.dist-info/METADATA
mola_workflow-2.0.0.dist-info/WHEEL
mola_workflow-2.0.0.dist-info/licenses/AUTHORS.md
mola_workflow-2.0.0.dist-info/licenses/LICENSE
mola_workflow-2.0.0.dist-info/RECORD
