Metadata-Version: 2.4
Name: mola-workflow
Version: 2.0.0
Summary: MOLA is an ONERA Python code that implements user-level workflows and tools for aerodynamic analysis
Project-URL: Homepage, https://github.com/onera/MOLA
Project-URL: Issues, https://github.com/onera/MOLA/issues
Author-email: Luis Bernardos <luisfco.bernardos@gmail.com>, Thomas Bontemps <thomas.bontemps@hotmail.fr>
License-File: AUTHORS.md
License-File: LICENSE
Classifier: License :: OSI Approved :: GNU Lesser General Public License v3 (LGPLv3)
Classifier: Operating System :: OS Independent
Classifier: Programming Language :: Python :: 3
Requires-Python: >=3.7
